pgpipe/__init__.py
pgpipe/cli.py
pgpipe/config.py
pgpipe/core.py
pgpipe/models.py
pgpipe/queries.py
pgpipe-1.0.5.dist-info/LICENSE
pgpipe-1.0.5.dist-info/METADATA
pgpipe-1.0.5.dist-info/WHEEL
pgpipe-1.0.5.dist-info/entry_points.txt
pgpipe-1.0.5.dist-info/RECORD
