Metadata-Version: 2.1
Name: pgpipe
Version: 1.0.5
Summary: 
Author: Robert Rode
Author-email: github@robertrode.com
Requires-Python: >=3.9,<4.0
Classifier: Programming Language :: Python :: 3
Classifier: Programming Language :: Python :: 3.9
Classifier: Programming Language :: Python :: 3.10
Classifier: Programming Language :: Python :: 3.11
Requires-Dist: loguru (>=0.7.0,<0.8.0)
Requires-Dist: psycopg[binary] (>=3.1.9,<4.0.0)
Requires-Dist: pydantic (>=2.0.3,<3.0.0)
Requires-Dist: pydantic-settings (>=2.0.2,<3.0.0)
